{
  "LFLS": {
    "elevation": 1302,
    "runways": "09,27,09R,27L",
    "transAlt": 5000,
    "maxInitialClimb": 7000,
    "appSI": "MM,LLA",
    "sids": {
      "BELEP": {
        "E": {
          "1": {
            "rwy": "09",
            "initial": 5000,
            "prio": 2,
            "equip": {
              "RNAV": true
            }
          }
        },
        "W": {
          "1": {
            "rwy": "27",
            "initial": 5000,
            "prio": 1,
            "equip": {
              "RNAV": true
            }
          }
        }
      },
      "BELUS": {
        "E": {
          "1": {
            "rwy": "09",
            "initial": 5000,
            "prio": 2,
            "equip": {
              "RNAV": true
            }
          }
        },
        "W": {
          "1": {
            "rwy": "27",
            "initial": 5000,
            "prio": 1,
            "equip": {
              "RNAV": true
            }
          }
        }
      },
      "DANBO": {
        "E": {
          "1": {
            "rwy": "09",
            "initial": 5000,
            "prio": 2,
            "equip": {
              "RNAV": true
            }
          }
        },
        "W": {
          "1": {
            "rwy": "27",
            "initial": 5000,
            "prio": 1,
            "equip": {
              "RNAV": true
            }
          }
        }
      },
      "MOKIP": {
        "E": {
          "1": {
            "rwy": "09",
            "initial": 5000,
            "prio": 2,
            "equip": {
              "RNAV": true
            }
          }
        },
        "W": {
          "1": {
            "rwy": "27",
            "initial": 5000,
            "prio": 1,
            "equip": {
              "RNAV": true
            }
          }
        }
      },
      "REPSI": {
        "E": {
          "1": {
            "rwy": "09",
            "initial": 5000,
            "prio": 2,
            "equip": {
              "RNAV": true
            }
          }
        },
        "W": {
          "1": {
            "rwy": "27",
            "initial": 5000,
            "prio": 1,
            "equip": {
              "RNAV": true
            }
          }
        }
      },
      "RISOR": {
        "E": {
          "1": {
            "rwy": "09",
            "initial": 7000,
            "prio": 2,
            "equip": {
              "RNAV": true
            }
          }
        },
        "W": {
          "1": {
            "rwy": "27",
            "initial": 7000,
            "prio": 1,
            "equip": {
              "RNAV": true
            }
          }
        }
      },
      "ROMAM": {
        "E": {
          "1": {
            "rwy": "09",
            "initial": 5000,
            "prio": 2,
            "equip": {
              "RNAV": true
            }
          }
        },
        "W": {
          "1": {
            "rwy": "27",
            "initial": 5000,
            "prio": 1,
            "equip": {
              "RNAV": true
            }
          }
        }
      },
      "PIRUV": {
        "E": {
          "1": {
            "rwy": "09",
            "initial": 5000,
            "prio": 2,
            "equip": {
              "RNAV": true
            }
          }
        },
        "W": {
          "1": {
            "rwy": "27",
            "initial": 5000,
            "prio": 1,
            "equip": {
              "RNAV": true
            }
          }
        }
      }
    }
  }
}